jaseci_ai_kit/VERSION
jaseci_ai_kit/__init__.py
jaseci_ai_kit/bart_sum.py
jaseci_ai_kit/bi_enc.py
jaseci_ai_kit/cl_summer.py
jaseci_ai_kit/cluster.py
jaseci_ai_kit/config.py
jaseci_ai_kit/ent_ext.py
jaseci_ai_kit/fast_enc.py
jaseci_ai_kit/pdf_ext.py
jaseci_ai_kit/ph.py
jaseci_ai_kit/sbert_sim.py
jaseci_ai_kit/stt.py
jaseci_ai_kit/t5_sum.py
jaseci_ai_kit/test_module.py
jaseci_ai_kit/text_seg.py
jaseci_ai_kit/tfm_ner.py
jaseci_ai_kit/topic_ext.py
jaseci_ai_kit/translator.py
jaseci_ai_kit/tts.py
jaseci_ai_kit/use_enc.py
jaseci_ai_kit/use_qa.py
jaseci_ai_kit/zs_classifier.py
jaseci_ai_kit/modules/__init__.py
jaseci_ai_kit/modules/bart_sum/__init__.py
jaseci_ai_kit/modules/bart_sum/bart_sum.py
jaseci_ai_kit/modules/cl_summer/__init__.py
jaseci_ai_kit/modules/cl_summer/action_config.py
jaseci_ai_kit/modules/cl_summer/cl_summer.py
jaseci_ai_kit/modules/cl_summer/tests/__init__.py
jaseci_ai_kit/modules/cl_summer/tests/test_cl_summer.py
jaseci_ai_kit/modules/cluster/__init__.py
jaseci_ai_kit/modules/cluster/cluster.py
jaseci_ai_kit/modules/cluster/tests/__init__.py
jaseci_ai_kit/modules/cluster/tests/test_cluster.py
jaseci_ai_kit/modules/encoders/__init__.py
jaseci_ai_kit/modules/encoders/action_config.py
jaseci_ai_kit/modules/encoders/bi_enc.py
jaseci_ai_kit/modules/encoders/poly_enc.py
jaseci_ai_kit/modules/encoders/sent_enc.py
jaseci_ai_kit/modules/encoders/tests/__init__.py
jaseci_ai_kit/modules/encoders/tests/test_bi_enc.py
jaseci_ai_kit/modules/encoders/utils/__init__.py
jaseci_ai_kit/modules/encoders/utils/evaluate.py
jaseci_ai_kit/modules/encoders/utils/model_config.json
jaseci_ai_kit/modules/encoders/utils/models.py
jaseci_ai_kit/modules/encoders/utils/tokenizer.py
jaseci_ai_kit/modules/encoders/utils/train.py
jaseci_ai_kit/modules/encoders/utils/train_config.json
jaseci_ai_kit/modules/ent_ext/__init__.py
jaseci_ai_kit/modules/ent_ext/action_config.py
jaseci_ai_kit/modules/ent_ext/config.cfg
jaseci_ai_kit/modules/ent_ext/ent_ext.py
jaseci_ai_kit-1.4.0.3.dist-info/METADATA
jaseci_ai_kit-1.4.0.3.dist-info/WHEEL
jaseci_ai_kit-1.4.0.3.dist-info/top_level.txt
jaseci_ai_kit-1.4.0.3.dist-info/RECORD
