Metadata-Version: 2.1
Name: jaseci-ai-kit
Version: 1.4.0.3
Home-page: https://github.com/Jaseci-Labs/jaseci
Author: Jason Mars
Author-email: jason@jaseci.org
Requires-Dist: jaseci
Requires-Dist: tensorflow (<3.0.0,>=2.8.0)
Requires-Dist: tensorflow-hub (<1.0.0,>=0.12.0)
Requires-Dist: tensorflow-text (<3.0.0,>=2.7.3)
Requires-Dist: transformers (==4.25.1)
Requires-Dist: torch (<2.0.0,>=1.10.2)
Requires-Dist: pandas (<2.0.0,>=1.4.1)
Requires-Dist: flair (==0.11.3)
Requires-Dist: numpy (<1.24.0,>=1.23.0)
Requires-Dist: fasttext (<0.10.0,>=0.9.2)
Requires-Dist: spacy (==3.3.0)
Requires-Dist: sumy (==0.11.0)
Requires-Dist: PyPDF2 (<1.28,>=1.27.12)
Requires-Dist: evaluate (<0.3,>=0.2.2)
Requires-Dist: seqeval (<1.3,>=1.2.2)
Requires-Dist: pytest (<7.1,>=7.0.1)
Requires-Dist: pytest-order (<1.1,>=1.0.1)
Requires-Dist: sentence-transformers (<2.3,>=2.2.0)
Requires-Dist: beautifulsoup4 (<4.11.0,>=4.10.0)
Requires-Dist: umap-learn (==0.5.3)
Requires-Dist: hdbscan (==0.8.29)
Requires-Dist: librosa (==0.9.2)
Requires-Dist: protobuf (<3.21,>=3.20.1)
Requires-Dist: inflect (<=6.0.2)
Requires-Dist: unidecode (==1.3.6)
Requires-Dist: soundfile (<=0.11.0)
Requires-Dist: speechbrain (==0.5.13)
